augmentts/__init__.py
augmentts/datasets.py
augmentts/utils.py
augmentts/augmenters/__init__.py
augmentts/augmenters/vae.py
augmentts/forecasters/deep.py
AugmentTS-0.1.0.dist-info/LICENSE
AugmentTS-0.1.0.dist-info/METADATA
AugmentTS-0.1.0.dist-info/WHEEL
AugmentTS-0.1.0.dist-info/top_level.txt
AugmentTS-0.1.0.dist-info/RECORD
