Metadata-Version: 2.1
Name: AugmentTS
Version: 0.1.0
Summary: Time Series Forecasting and Data Augmentation using Deep Generative Models 
Home-page: https://github.com/DrSasanBarak/AugmentTS
Author: Sasan Barak
Author-email: s.barak@soton.ac.uk
License: UNKNOWN
Platform: UNKNOWN
License-File: LICENSE
Requires-Dist: tensorflow (>=2.0.0)
Requires-Dist: keras
Requires-Dist: tensorflow-addons
Requires-Dist: sktime (>=0.7.0)
